acetolang/__init__.py
acetolang/__main__.py
acetolang-1.10.2.dist-info/entry_points.txt
acetolang-1.10.2.dist-info/WHEEL
acetolang-1.10.2.dist-info/METADATA
acetolang-1.10.2.dist-info/RECORD
